setup.py
src/Ifbyphone/__init__.py
src/Ifbyphone/client.py
src/Ifbyphone/api/__init__.py
src/Ifbyphone/api/addons.py
src/Ifbyphone/api/base.py
src/Ifbyphone/api/broadcast.py
src/Ifbyphone/api/clicktocall.py
src/Ifbyphone/api/clicktofindme.py
src/Ifbyphone/api/clicktofindmelist.py
src/Ifbyphone/api/clicktosurvo.py
src/Ifbyphone/api/clicktovoicemail.py
src/Ifbyphone/api/clicktovr.py
src/Ifbyphone/api/conference.py
src/Ifbyphone/api/cost.py
src/Ifbyphone/api/findme.py
src/Ifbyphone/api/general.py
src/Ifbyphone/api/group.py
src/Ifbyphone/api/locator.py
src/Ifbyphone/api/numbers.py
src/Ifbyphone/api/recordings.py
src/Ifbyphone/api/registernumbers.py
src/Ifbyphone/api/report.py
src/Ifbyphone/api/routing.py
src/Ifbyphone/api/sms.py
src/Ifbyphone/api/survo.py
src/Ifbyphone/api/transcription.py
src/Ifbyphone/api/verifymenow.py
src/Ifbyphone/api/voicemail.py
src/Ifbyphone_API_Module.egg-info/PKG-INFO
src/Ifbyphone_API_Module.egg-info/SOURCES.txt
src/Ifbyphone_API_Module.egg-info/dependency_links.txt
src/Ifbyphone_API_Module.egg-info/requires.txt
src/Ifbyphone_API_Module.egg-info/top_level.txt