Metadata-Version: 1.0
Name: Ifbyphone-API-Module
Version: 0.0.5
Summary: A Python client for interacting with Ifbyphone REST API
Home-page: https://github.com/Opus1no2/Ifbyphone-API-Module
Author: Travis Tillotson
Author-email: tillotson.travis@gmail.com
License: MIT
Platform: UNKNOWN
